lqrt/__init__.py
lqrt/lqrt.py
lqrt-0.3.3.dist-info/LICENSE
lqrt-0.3.3.dist-info/METADATA
lqrt-0.3.3.dist-info/WHEEL
lqrt-0.3.3.dist-info/top_level.txt
lqrt-0.3.3.dist-info/RECORD
