Metadata-Version: 2.1
Name: lqrt
Version: 0.3.3
Summary: Robust Hypothesis Testing of Location Parameters using Lq-Likelihood-Ratio-Type Test in Python
Home-page: https://github.com/alyakin314/lqrt
Author: Anton Alyakin
Author-email: aalyaki1@jhu.edu
License: UNKNOWN
Platform: UNKNOWN
Classifier: Programming Language :: Python :: 3
Classifier: Operating System :: OS Independent
Requires-Dist: numpy
Requires-Dist: scipy
